<?xml version="1.0" encoding="UTF-8"?>
<odoo>

		<record id="view_email_server_form" model="ir.ui.view">
			<field name="name">fetchmail.server.company.form</field>
			<field name="model">fetchmail.server</field>
			<field name="groups_id" eval="[(6, 0, [ref('base.group_multi_company')])]"/>
			<field name="inherit_id" ref="fetchmail.view_email_server_form" />
			<field name="arch" type="xml">

				<field name="name" position="after">
					<field name="company_id" />
				</field>

			</field>
		</record>

</odoo>